google/genai/__init__.py
google/genai/_api_client.py
google/genai/_api_module.py
google/genai/_automatic_function_calling_util.py
google/genai/_common.py
google/genai/_extra_utils.py
google/genai/_replay_api_client.py
google/genai/_test_api_client.py
google/genai/_transformers.py
google/genai/batches.py
google/genai/caches.py
google/genai/chats.py
google/genai/client.py
google/genai/errors.py
google/genai/files.py
google/genai/live.py
google/genai/models.py
google/genai/operations.py
google/genai/pagers.py
google/genai/tunings.py
google/genai/types.py
google/genai/version.py
google_genai_aipy-1.9.0.dist-info/METADATA
google_genai_aipy-1.9.0.dist-info/WHEEL
google_genai_aipy-1.9.0.dist-info/top_level.txt
google_genai_aipy-1.9.0.dist-info/RECORD
