Metadata-Version: 2.4
Name: google-genai-aipy
Version: 1.9.0
Summary: Google GenAI Python SDK
Author-email: The QPYPI Team <qpypi@qpython.org>
License: MIT AND (Apache-2.0 OR BSD-2-Clause)
Project-URL: Homepage, https://qpypi.qpython.org/project/google-genai-aipy/
Classifier: Intended Audience :: Developers
Classifier: Intended Audience :: Education
Classifier: Intended Audience :: Information Technology
Classifier: Intended Audience :: End Users/Desktop
Classifier: License :: OSI Approved :: Apache Software License
Classifier: Operating System :: Android
Classifier: Programming Language :: Python
Classifier: Programming Language :: Python :: 3.12
Classifier: Topic :: Software Development
Requires-Python: ==3.12.*
Requires-Dist: anyio<5.0.0,>=4.8.0
Requires-Dist: google-auth<3.0.0,>=2.14.1
Requires-Dist: httpx<1.0.0,>=0.28.1
Requires-Dist: pydantic-qpython
Requires-Dist: requests<3.0.0,>=2.28.1
Requires-Dist: websockets<15.1.0,>=13.0.0
Requires-Dist: typing-extensions-qpython
